pyChemometrics/ChemometricsPCA.py
pyChemometrics/ChemometricsPLS.py
pyChemometrics/ChemometricsPLSDA.py
pyChemometrics/ChemometricsPLS_LDA.py
pyChemometrics/ChemometricsPLS_Logistic.py
pyChemometrics/ChemometricsScaler.py
pyChemometrics/PCAPlotMixin.py
pyChemometrics/PLSDAPlotMixin.py
pyChemometrics/PLSPlotMixin.py
pyChemometrics/PlotMixin.py
pyChemometrics/__init__.py
pyChemometrics-0.13.6.dist-info/LICENSE
pyChemometrics-0.13.6.dist-info/METADATA
pyChemometrics-0.13.6.dist-info/WHEEL
pyChemometrics-0.13.6.dist-info/top_level.txt
pyChemometrics-0.13.6.dist-info/RECORD
