Metadata-Version: 2.1
Name: pyChemometrics
Version: 0.13.6
Summary: The pyChemometrics provides objects which wrap pre-existing scikit-learn PCA and PLS algorithms and adds model assessment metrics and functions common in the Chemometrics literature.
Home-page: https://github.com/Gscorreia89/pyChemometrics/
Author: Gonçalo Correia
Author-email: gscorreia89@gmail.com
License: BSD 3-Clause License
Platform: UNKNOWN
